samo/__init__.py
samo/__main__.py
samo/cli.py
samo/backend/__init__.py
samo/backend/fpgaconvnet/__init__.py
samo/backend/fpgaconvnet/export.py
samo/backend/fpgaconvnet/node.py
samo/backend/fpgaconvnet/parser.py
samo/model/__init__.py
samo/model/network.py
samo/model/node.py
samo/model/partition.py
samo/optimiser/__init__.py
samo/optimiser/annealing.py
samo/optimiser/brute.py
samo/optimiser/rule.py
samo-0.2.4.dist-info/LICENSE
samo-0.2.4.dist-info/METADATA
samo-0.2.4.dist-info/WHEEL
samo-0.2.4.dist-info/top_level.txt
samo-0.2.4.dist-info/RECORD
