Metadata-Version: 2.1
Name: samo
Version: 0.2.4
Summary: Streaming Architecture Mapping Optimiser
Home-page: https://github.com/AlexMontgomerie/samo
Author: Alex Montgomerie, Zhewen Yu
Author-email: am9215@ic.ac.uk
Classifier: Programming Language :: Python :: 3
Classifier: Operating System :: OS Independent
Requires-Python: >=3.8
License-File: LICENSE
Requires-Dist: networkx (>=2.5)
Requires-Dist: tqdm (>=4.62.3)
Requires-Dist: numpy (>=1.19.2)
Requires-Dist: tabulate (>=0.8.9)
